boxfit/__init__.py
boxfit/boxfit.py
boxfit-0.1.0.dist-info/METADATA
boxfit-0.1.0.dist-info/WHEEL
boxfit-0.1.0.dist-info/licenses/LICENSE
boxfit-0.1.0.dist-info/RECORD
