Metadata-Version: 2.4
Name: boxfit
Version: 0.1.0
Summary: A fitting algorithm for volumetric hits caused by limited detector resolution
Project-URL: Homepage, https://github.com/calebmiller/boxfit
Project-URL: Issues, https://github.com/calebmiller/boxfit/issues
Author-email: Caleb Miller <calebmiller@uvic.ca>
License-File: LICENSE
Classifier: License :: OSI Approved :: MIT License
Classifier: Operating System :: OS Independent
Classifier: Programming Language :: Python :: 3
Requires-Python: >=3.8
